{
  "mentions": [
    {
      "volume": {
        "link": "http://tolstoy.ru/online/90/05/", 
        "number": 5, 
        "name": "Произведения, 1856—1859"
      }, 
      "mentions": [
        {
          "comment": 0, 
          "start": 254, 
          "end": 254
        }, 
        {
          "comment": 0, 
          "start": 252, 
          "end": 252
        }
      ]
    }, 
    {
      "volume": {
        "link": "http://tolstoy.ru/online/90/07/", 
        "number": 7, 
        "name": "Произведения, 1856—1869"
      }, 
      "mentions": [
        {
          "comment": 1, 
          "start": 349, 
          "end": 349
        }
      ]
    }, 
    {
      "volume": {
        "link": "http://tolstoy.ru/online/90/47/", 
        "number": 47, 
        "name": "Дневники и записные книжки, 1854—1857"
      }, 
      "mentions": [
        {
          "comment": 1, 
          "start": 143, 
          "end": 143
        }
      ]
    }
  ]
}