{
  "mentions": [
    {
      "volume": {
        "link": "http://tolstoy.ru/online/90/17/", 
        "number": 17, 
        "name": "Произведения, 1863, 1870, 1872—1879, 1884"
      }, 
      "mentions": [
        {
          "comment": 0, 
          "start": 63, 
          "end": 63
        }
      ]
    }, 
    {
      "volume": {
        "link": "http://tolstoy.ru/online/90/49/", 
        "number": 49, 
        "name": "Записки христианина, дневники и записные книжки, 1881—1887"
      }, 
      "mentions": [
        {
          "comment": 0, 
          "start": 55, 
          "end": 55
        }
      ]
    }, 
    {
      "volume": {
        "link": "http://tolstoy.ru/online/90/53/", 
        "number": 53, 
        "name": "Дневники и записные книжки, 1895—1899"
      }, 
      "mentions": [
        {
          "comment": 0, 
          "start": 145, 
          "end": 145
        }
      ]
    }, 
    {
      "volume": {
        "link": "http://tolstoy.ru/online/90/62/", 
        "number": 62, 
        "name": "Письма, 1873—1879"
      }, 
      "mentions": [
        {
          "comment": 0, 
          "start": 38, 
          "end": 38
        }
      ]
    }, 
    {
      "volume": {
        "link": "http://tolstoy.ru/online/90/63/", 
        "number": 63, 
        "name": "Письма, 1880—1886"
      }, 
      "mentions": [
        {
          "comment": 0, 
          "start": 195, 
          "end": 195
        }
      ]
    }, 
    {
      "volume": {
        "link": "http://tolstoy.ru/online/90/66/", 
        "number": 66, 
        "name": "Письма, 1891 (июль — декабрь)"
      }, 
      "mentions": [
        {
          "comment": 0, 
          "start": 121, 
          "end": 121
        }
      ]
    }, 
    {
      "volume": {
        "link": "http://tolstoy.ru/online/90/83/", 
        "number": 83, 
        "name": "Письма к С. А. Толстой, 1862—1886"
      }, 
      "mentions": [
        {
          "comment": 0, 
          "start": 383, 
          "end": 383
        }, 
        {
          "comment": 0, 
          "start": 382, 
          "end": 382
        }, 
        {
          "comment": 0, 
          "start": 293, 
          "end": 293
        }
      ]
    }
  ]
}