{
  "mentions": [
    {
      "volume": {
        "link": "http://tolstoy.ru/online/90/54/", 
        "number": 54, 
        "name": "Дневники, записные книжки и отдельные записки, 1900—1903"
      }, 
      "mentions": [
        {
          "comment": 0, 
          "start": 229, 
          "end": 229
        }, 
        {
          "comment": 0, 
          "start": 228, 
          "end": 228
        }
      ]
    }, 
    {
      "volume": {
        "link": "http://tolstoy.ru/online/90/56/", 
        "number": 56, 
        "name": "Дневники, записные книжки и отдельные записки, 1907—1908"
      }, 
      "mentions": [
        {
          "comment": 0, 
          "start": 290, 
          "end": 290
        }
      ]
    }
  ]
}