{
  "mentions": [
    {
      "volume": {
        "link": "http://tolstoy.ru/online/90/51/", 
        "number": 51, 
        "name": "Дневники и записные книжки, 1890"
      }, 
      "mentions": [
        {
          "comment": 1, 
          "start": 248, 
          "end": 248
        }, 
        {
          "comment": 1, 
          "start": 209, 
          "end": 209
        }, 
        {
          "comment": 1, 
          "start": 177, 
          "end": 177
        }, 
        {
          "comment": 1, 
          "start": 163, 
          "end": 163
        }, 
        {
          "comment": 0, 
          "start": 158, 
          "end": 158
        }, 
        {
          "comment": 0, 
          "start": 70, 
          "end": 70
        }
      ]
    }
  ]
}