{
  "mentions": [
    {
      "volume": {
        "link": "http://tolstoy.ru/online/90/41/", 
        "number": 41, 
        "name": "Круг чтения. Том первый"
      }, 
      "mentions": [
        {
          "comment": 0, 
          "start": 321, 
          "end": 321
        }
      ]
    }, 
    {
      "volume": {
        "link": "http://tolstoy.ru/online/90/44/", 
        "number": 44, 
        "name": "На каждый день. Часть 2"
      }, 
      "mentions": [
        {
          "comment": 0, 
          "start": 125, 
          "end": 125
        }
      ]
    }, 
    {
      "volume": {
        "link": "http://tolstoy.ru/online/90/45/", 
        "number": 45, 
        "name": "Путь жизни"
      }, 
      "mentions": [
        {
          "comment": 0, 
          "start": 459, 
          "end": 459
        }
      ]
    }
  ]
}