{
  "mentions": [
    {
      "volume": {
        "link": "http://tolstoy.ru/online/90/77/", 
        "number": 77, 
        "name": "Письма, 1907—1908"
      }, 
      "mentions": [
        {
          "comment": 0, 
          "start": 255, 
          "end": 255
        }
      ]
    }, 
    {
      "volume": {
        "link": "http://tolstoy.ru/online/90/89/", 
        "number": 89, 
        "name": "Письма к В. Г. Черткову. 1905—1910"
      }, 
      "mentions": [
        {
          "comment": 0, 
          "start": 84, 
          "end": 84
        }
      ]
    }
  ]
}