{
  "mentions": [
    {
      "volume": {
        "link": "http://tolstoy.ru/online/90/66/", 
        "number": 66, 
        "name": "Письма, 1891 (июль — декабрь)"
      }, 
      "mentions": [
        {
          "comment": 1, 
          "start": 51, 
          "end": 51
        }, 
        {
          "comment": 1, 
          "start": 43, 
          "end": 43
        }
      ]
    }, 
    {
      "volume": {
        "link": "http://tolstoy.ru/online/90/87/", 
        "number": 87, 
        "name": "Письма к В. Г. Черткову, 1890—1896"
      }, 
      "mentions": [
        {
          "comment": 1, 
          "start": 116, 
          "end": 116
        }, 
        {
          "comment": 0, 
          "start": 113, 
          "end": 113
        }, 
        {
          "comment": 1, 
          "start": 105, 
          "end": 105
        }, 
        {
          "comment": 0, 
          "start": 104, 
          "end": 104
        }, 
        {
          "comment": 1, 
          "start": 99, 
          "end": 99
        }, 
        {
          "comment": 0, 
          "start": 98, 
          "end": 98
        }, 
        {
          "comment": 1, 
          "start": 96, 
          "end": 96
        }, 
        {
          "comment": 0, 
          "start": 94, 
          "end": 94
        }, 
        {
          "comment": 0, 
          "start": 92, 
          "end": 92
        }, 
        {
          "comment": 1, 
          "start": 92, 
          "end": 92
        }, 
        {
          "comment": 1, 
          "start": 86, 
          "end": 86
        }, 
        {
          "comment": 0, 
          "start": 85, 
          "end": 85
        }, 
        {
          "comment": 1, 
          "start": 85, 
          "end": 85
        }
      ]
    }
  ]
}