{
  "mentions": [
    {
      "volume": {
        "link": "http://tolstoy.ru/online/90/04/", 
        "number": 4, 
        "name": "Произведения севастопольского периода. Утро помещика"
      }, 
      "mentions": [
        {
          "comment": 1, 
          "start": 399, 
          "end": 399
        }
      ]
    }, 
    {
      "volume": {
        "link": "http://tolstoy.ru/online/90/05/", 
        "number": 5, 
        "name": "Произведения, 1856—1859"
      }, 
      "mentions": [
        {
          "comment": 1, 
          "start": 328, 
          "end": 328
        }, 
        {
          "comment": 1, 
          "start": 322, 
          "end": 322
        }
      ]
    }, 
    {
      "volume": {
        "link": "http://tolstoy.ru/online/90/47/", 
        "number": 47, 
        "name": "Дневники и записные книжки, 1854—1857"
      }, 
      "mentions": [
        {
          "comment": 1, 
          "start": 517, 
          "end": 517
        }, 
        {
          "comment": 1, 
          "start": 515, 
          "end": 515
        }, 
        {
          "comment": 1, 
          "start": 397, 
          "end": 397
        }, 
        {
          "comment": 1, 
          "start": 328, 
          "end": 328
        }, 
        {
          "comment": 0, 
          "start": 165, 
          "end": 165
        }, 
        {
          "comment": 0, 
          "start": 164, 
          "end": 164
        }, 
        {
          "comment": 0, 
          "start": 76, 
          "end": 76
        }, 
        {
          "comment": 0, 
          "start": 74, 
          "end": 74
        }
      ]
    }, 
    {
      "volume": {
        "link": "http://tolstoy.ru/online/90/48/", 
        "number": 48, 
        "name": "Дневники и записные книжки, 1858—1880"
      }, 
      "mentions": [
        {
          "comment": 1, 
          "start": 476, 
          "end": 476
        }, 
        {
          "comment": 0, 
          "start": 64, 
          "end": 64
        }, 
        {
          "comment": 0, 
          "start": 63, 
          "end": 63
        }
      ]
    }, 
    {
      "volume": {
        "link": "http://tolstoy.ru/online/90/49/", 
        "number": 49, 
        "name": "Записки христианина, дневники и записные книжки, 1881—1887"
      }, 
      "mentions": [
        {
          "comment": 1, 
          "start": 198, 
          "end": 198
        }, 
        {
          "comment": 0, 
          "start": 36, 
          "end": 36
        }
      ]
    }, 
    {
      "volume": {
        "link": "http://tolstoy.ru/online/90/54/", 
        "number": 54, 
        "name": "Дневники, записные книжки и отдельные записки, 1900—1903"
      }, 
      "mentions": [
        {
          "comment": 1, 
          "start": 435, 
          "end": 435
        }, 
        {
          "comment": 1, 
          "start": 382, 
          "end": 382
        }, 
        {
          "comment": 0, 
          "start": 53, 
          "end": 53
        }
      ]
    }, 
    {
      "volume": {
        "link": "http://tolstoy.ru/online/90/72/", 
        "number": 72, 
        "name": "Письма, 1899—1900"
      }, 
      "mentions": [
        {
          "comment": 1, 
          "start": 499, 
          "end": 499
        }, 
        {
          "comment": 0, 
          "start": 498, 
          "end": 498
        }
      ]
    }, 
    {
      "volume": {
        "link": "http://tolstoy.ru/online/90/73/", 
        "number": 73, 
        "name": "Письма, 1901—1902"
      }, 
      "mentions": [
        {
          "comment": 0, 
          "start": 249, 
          "end": 249
        }, 
        {
          "comment": 1, 
          "start": 249, 
          "end": 249
        }
      ]
    }, 
    {
      "volume": {
        "link": "http://tolstoy.ru/online/90/74/", 
        "number": 74, 
        "name": "Письма, 1903"
      }, 
      "mentions": [
        {
          "comment": 1, 
          "start": 140, 
          "end": 140
        }, 
        {
          "comment": 0, 
          "start": 139, 
          "end": 139
        }
      ]
    }, 
    {
      "volume": {
        "link": "http://tolstoy.ru/online/90/83/", 
        "number": 83, 
        "name": "Письма к С. А. Толстой, 1862—1886"
      }, 
      "mentions": [
        {
          "comment": 0, 
          "start": 240, 
          "end": 240
        }, 
        {
          "comment": 1, 
          "start": 240, 
          "end": 240
        }, 
        {
          "comment": 1, 
          "start": 165, 
          "end": 165
        }, 
        {
          "comment": 0, 
          "start": 163, 
          "end": 163
        }
      ]
    }, 
    {
      "volume": {
        "link": "http://tolstoy.ru/online/90/84/", 
        "number": 84, 
        "name": "Письма к С. А. Толстой, 1887—1910"
      }, 
      "mentions": [
        {
          "comment": 0, 
          "start": 351, 
          "end": 351
        }, 
        {
          "comment": 1, 
          "start": 351, 
          "end": 351
        }
      ]
    }
  ]
}