{
  "mentions": [
    {
      "volume": {
        "link": "http://tolstoy.ru/online/90/13/", 
        "number": 13, 
        "name": "Война и мир: Черновые редакции и варианты (Часть 1)"
      }, 
      "mentions": [
        {
          "comment": 0, 
          "start": 541, 
          "end": 541
        }, 
        {
          "comment": 0, 
          "start": 537, 
          "end": 537
        }, 
        {
          "comment": 0, 
          "start": 520, 
          "end": 520
        }, 
        {
          "comment": 0, 
          "start": 146, 
          "end": 146
        }, 
        {
          "comment": 0, 
          "start": 144, 
          "end": 144
        }, 
        {
          "comment": 0, 
          "start": 140, 
          "end": 140
        }, 
        {
          "comment": 0, 
          "start": 139, 
          "end": 139
        }
      ]
    }
  ]
}