{
  "mentions": [
    {
      "volume": {
        "link": "http://tolstoy.ru/online/90/35/", 
        "number": 35, 
        "name": "Произведения, 1902—1904"
      }, 
      "mentions": [
        {
          "comment": 0, 
          "start": 246, 
          "end": 246
        }
      ]
    }, 
    {
      "volume": {
        "link": "http://tolstoy.ru/online/90/39/", 
        "number": 39, 
        "name": "Статьи, 1893—1898. Произведения, 1886, 1903—1909"
      }, 
      "mentions": [
        {
          "comment": 0, 
          "start": 43, 
          "end": 43
        }
      ]
    }
  ]
}