{
  "mentions": [
    {
      "volume": {
        "link": "http://tolstoy.ru/online/90/23/", 
        "number": 23, 
        "name": "Произведения, 1879—1884"
      }, 
      "mentions": [
        {
          "comment": 0, 
          "start": 327, 
          "end": 327
        }
      ]
    }, 
    {
      "volume": {
        "link": "http://tolstoy.ru/online/90/25/", 
        "number": 25, 
        "name": "Произведения 1880-х годов"
      }, 
      "mentions": [
        {
          "comment": 0, 
          "start": 344, 
          "end": 344
        }
      ]
    }, 
    {
      "volume": {
        "link": "http://tolstoy.ru/online/90/28/", 
        "number": 28, 
        "name": "Царство божие внутри вас"
      }, 
      "mentions": [
        {
          "comment": 1, 
          "start": 349, 
          "end": 349
        }, 
        {
          "comment": 1, 
          "start": 348, 
          "end": 348
        }, 
        {
          "comment": 0, 
          "start": 223, 
          "end": 223
        }, 
        {
          "comment": 0, 
          "start": 152, 
          "end": 152
        }, 
        {
          "comment": 0, 
          "start": 131, 
          "end": 131
        }
      ]
    }, 
    {
      "volume": {
        "link": "http://tolstoy.ru/online/90/30/", 
        "number": 30, 
        "name": "Произведения, 1882—1898"
      }, 
      "mentions": [
        {
          "comment": 0, 
          "start": 173, 
          "end": 173
        }, 
        {
          "comment": 0, 
          "start": 171, 
          "end": 171
        }
      ]
    }, 
    {
      "volume": {
        "link": "http://tolstoy.ru/online/90/33/", 
        "number": 33, 
        "name": "Воскресение: Черновые редакции и варианты"
      }, 
      "mentions": [
        {
          "comment": 0, 
          "start": 213, 
          "end": 213
        }
      ]
    }, 
    {
      "volume": {
        "link": "http://tolstoy.ru/online/90/35/", 
        "number": 35, 
        "name": "Произведения, 1902—1904"
      }, 
      "mentions": [
        {
          "comment": 0, 
          "start": 202, 
          "end": 202
        }, 
        {
          "comment": 0, 
          "start": 174, 
          "end": 174
        }, 
        {
          "comment": 0, 
          "start": 173, 
          "end": 173
        }
      ]
    }, 
    {
      "volume": {
        "link": "http://tolstoy.ru/online/90/36/", 
        "number": 36, 
        "name": "Произведения, 1904—1906"
      }, 
      "mentions": [
        {
          "comment": 1, 
          "start": 696, 
          "end": 696
        }, 
        {
          "comment": 0, 
          "start": 520, 
          "end": 520
        }, 
        {
          "comment": 0, 
          "start": 294, 
          "end": 294
        }, 
        {
          "comment": 0, 
          "start": 198, 
          "end": 198
        }
      ]
    }, 
    {
      "volume": {
        "link": "http://tolstoy.ru/online/90/38/", 
        "number": 38, 
        "name": "Произведения, 1909—1910"
      }, 
      "mentions": [
        {
          "comment": 1, 
          "start": 543, 
          "end": 543
        }, 
        {
          "comment": 1, 
          "start": 542, 
          "end": 542
        }, 
        {
          "comment": 1, 
          "start": 511, 
          "end": 511
        }, 
        {
          "comment": 1, 
          "start": 510, 
          "end": 510
        }, 
        {
          "comment": 0, 
          "start": 343, 
          "end": 343
        }, 
        {
          "comment": 0, 
          "start": 329, 
          "end": 329
        }, 
        {
          "comment": 0, 
          "start": 167, 
          "end": 167
        }, 
        {
          "comment": 0, 
          "start": 165, 
          "end": 165
        }, 
        {
          "comment": 0, 
          "start": 162, 
          "end": 162
        }, 
        {
          "comment": 0, 
          "start": 74, 
          "end": 74
        }, 
        {
          "comment": 0, 
          "start": 56, 
          "end": 56
        }
      ]
    }, 
    {
      "volume": {
        "link": "http://tolstoy.ru/online/90/44/", 
        "number": 44, 
        "name": "На каждый день. Часть 2"
      }, 
      "mentions": [
        {
          "comment": 1, 
          "start": 473, 
          "end": 473
        }
      ]
    }, 
    {
      "volume": {
        "link": "http://tolstoy.ru/online/90/46/", 
        "number": 46, 
        "name": "Дневник, 1847—1854"
      }, 
      "mentions": [
        {
          "comment": 1, 
          "start": 449, 
          "end": 449
        }
      ]
    }, 
    {
      "volume": {
        "link": "http://tolstoy.ru/online/90/51/", 
        "number": 51, 
        "name": "Дневники и записные книжки, 1890"
      }, 
      "mentions": [
        {
          "comment": 1, 
          "start": 205, 
          "end": 205
        }, 
        {
          "comment": 0, 
          "start": 61, 
          "end": 61
        }
      ]
    }, 
    {
      "volume": {
        "link": "http://tolstoy.ru/online/90/54/", 
        "number": 54, 
        "name": "Дневники, записные книжки и отдельные записки, 1900—1903"
      }, 
      "mentions": [
        {
          "comment": 1, 
          "start": 570, 
          "end": 570
        }, 
        {
          "comment": 0, 
          "start": 60, 
          "end": 60
        }
      ]
    }, 
    {
      "volume": {
        "link": "http://tolstoy.ru/online/90/55/", 
        "number": 55, 
        "name": "Дневники и записные книжки, 1904—1906"
      }, 
      "mentions": [
        {
          "comment": 1, 
          "start": 513, 
          "end": 513
        }, 
        {
          "comment": 0, 
          "start": 158, 
          "end": 158
        }
      ]
    }, 
    {
      "volume": {
        "link": "http://tolstoy.ru/online/90/65/", 
        "number": 65, 
        "name": "Письма, 1890—1891 (январь — июнь)"
      }, 
      "mentions": [
        {
          "comment": 0, 
          "start": 133, 
          "end": 133
        }
      ]
    }, 
    {
      "volume": {
        "link": "http://tolstoy.ru/online/90/81/", 
        "number": 81, 
        "name": "Письма, 1910"
      }, 
      "mentions": [
        {
          "comment": 0, 
          "start": 117, 
          "end": 117
        }
      ]
    }, 
    {
      "volume": {
        "link": "http://tolstoy.ru/online/90/87/", 
        "number": 87, 
        "name": "Письма к В. Г. Черткову, 1890—1896"
      }, 
      "mentions": [
        {
          "comment": 1, 
          "start": 89, 
          "end": 89
        }
      ]
    }
  ]
}