{
  "mentions": [
    {
      "volume": {
        "link": "http://tolstoy.ru/online/90/48/", 
        "number": 48, 
        "name": "Дневники и записные книжки, 1858—1880"
      }, 
      "mentions": [
        {
          "comment": 0, 
          "start": 166, 
          "end": 166
        }
      ]
    }, 
    {
      "volume": {
        "link": "http://tolstoy.ru/online/90/59/", 
        "number": 59, 
        "name": "Письма, 1844—1855"
      }, 
      "mentions": [
        {
          "comment": 1, 
          "start": 35, 
          "end": 35
        }, 
        {
          "comment": 1, 
          "start": 34, 
          "end": 34
        }, 
        {
          "comment": 0, 
          "start": 29, 
          "end": 29
        }, 
        {
          "comment": 1, 
          "start": 20, 
          "end": 20
        }, 
        {
          "comment": 0, 
          "start": 19, 
          "end": 19
        }, 
        {
          "comment": 0, 
          "start": 18, 
          "end": 18
        }
      ]
    }
  ]
}