{
  "mentions": [
    {
      "volume": {
        "link": "http://tolstoy.ru/online/90/13/", 
        "number": 13, 
        "name": "Война и мир: Черновые редакции и варианты (Часть 1)"
      }, 
      "mentions": [
        {
          "comment": 0, 
          "start": 687, 
          "end": 687
        }, 
        {
          "comment": 0, 
          "start": 601, 
          "end": 601
        }
      ]
    }, 
    {
      "volume": {
        "link": "http://tolstoy.ru/online/90/39/", 
        "number": 39, 
        "name": "Статьи, 1893—1898. Произведения, 1886, 1903—1909"
      }, 
      "mentions": [
        {
          "comment": 0, 
          "start": 217, 
          "end": 217
        }
      ]
    }
  ]
}