{
  "mentions": [
    {
      "volume": {
        "link": "http://tolstoy.ru/online/90/79/", 
        "number": 79, 
        "name": "Письма, 1909"
      }, 
      "mentions": [
        {
          "comment": 1, 
          "start": 283, 
          "end": 283
        }
      ]
    }, 
    {
      "volume": {
        "link": "http://tolstoy.ru/online/90/80/", 
        "number": 80, 
        "name": "Письма, 1909 (июль — декабрь)"
      }, 
      "mentions": [
        {
          "comment": 1, 
          "start": 294, 
          "end": 294
        }, 
        {
          "comment": 1, 
          "start": 291, 
          "end": 291
        }
      ]
    }, 
    {
      "volume": {
        "link": "http://tolstoy.ru/online/90/82/", 
        "number": 82, 
        "name": "Письма, 1910 (май — ноябрь)"
      }, 
      "mentions": [
        {
          "comment": 1, 
          "start": 242, 
          "end": 242
        }, 
        {
          "comment": 1, 
          "start": 238, 
          "end": 238
        }
      ]
    }
  ]
}