{
  "mentions": [
    {
      "volume": {
        "link": "http://tolstoy.ru/online/90/56/", 
        "number": 56, 
        "name": "Дневники, записные книжки и отдельные записки, 1907—1908"
      }, 
      "mentions": [
        {
          "comment": 1, 
          "start": 531, 
          "end": 531
        }
      ]
    }, 
    {
      "volume": {
        "link": "http://tolstoy.ru/online/90/67/", 
        "number": 67, 
        "name": "Письма, 1894"
      }, 
      "mentions": [
        {
          "comment": 1, 
          "start": 127, 
          "end": 127
        }
      ]
    }, 
    {
      "volume": {
        "link": "http://tolstoy.ru/online/90/68/", 
        "number": 68, 
        "name": "Письма, 1895"
      }, 
      "mentions": [
        {
          "comment": 1, 
          "start": 48, 
          "end": 48
        }, 
        {
          "comment": 0, 
          "start": 46, 
          "end": 46
        }
      ]
    }, 
    {
      "volume": {
        "link": "http://tolstoy.ru/online/90/77/", 
        "number": 77, 
        "name": "Письма, 1907—1908"
      }, 
      "mentions": [
        {
          "comment": 1, 
          "start": 8, 
          "end": 8
        }, 
        {
          "comment": 0, 
          "start": 7, 
          "end": 7
        }, 
        {
          "comment": 1, 
          "start": 7, 
          "end": 7
        }
      ]
    }, 
    {
      "volume": {
        "link": "http://tolstoy.ru/online/90/85/", 
        "number": 85, 
        "name": "Письма к В. Г. Черткову, 1883—1886"
      }, 
      "mentions": [
        {
          "comment": 1, 
          "start": 228, 
          "end": 228
        }
      ]
    }, 
    {
      "volume": {
        "link": "http://tolstoy.ru/online/90/87/", 
        "number": 87, 
        "name": "Письма к В. Г. Черткову, 1890—1896"
      }, 
      "mentions": [
        {
          "comment": 1, 
          "start": 319, 
          "end": 319
        }, 
        {
          "comment": 0, 
          "start": 318, 
          "end": 318
        }
      ]
    }, 
    {
      "volume": {
        "link": "http://tolstoy.ru/online/90/88/", 
        "number": 88, 
        "name": "Письма к В. Г. Черткову, 1897—1910"
      }, 
      "mentions": [
        {
          "comment": 1, 
          "start": 186, 
          "end": 186
        }, 
        {
          "comment": 0, 
          "start": 185, 
          "end": 185
        }
      ]
    }
  ]
}