{
  "mentions": [
    {
      "volume": {
        "link": "http://tolstoy.ru/online/90/53/", 
        "number": 53, 
        "name": "Дневники и записные книжки, 1895—1899"
      }, 
      "mentions": [
        {
          "comment": 1, 
          "start": 497, 
          "end": 497
        }, 
        {
          "comment": 0, 
          "start": 193, 
          "end": 193
        }
      ]
    }, 
    {
      "volume": {
        "link": "http://tolstoy.ru/online/90/71/", 
        "number": 71, 
        "name": "Письма, 1898"
      }, 
      "mentions": [
        {
          "comment": 1, 
          "start": 361, 
          "end": 361
        }, 
        {
          "comment": 0, 
          "start": 360, 
          "end": 360
        }
      ]
    }, 
    {
      "volume": {
        "link": "http://tolstoy.ru/online/90/84/", 
        "number": 84, 
        "name": "Письма к С. А. Толстой, 1887—1910"
      }, 
      "mentions": [
        {
          "comment": 0, 
          "start": 315, 
          "end": 315
        }, 
        {
          "comment": 0, 
          "start": 311, 
          "end": 311
        }
      ]
    }, 
    {
      "volume": {
        "link": "http://tolstoy.ru/online/90/88/", 
        "number": 88, 
        "name": "Письма к В. Г. Черткову, 1897—1910"
      }, 
      "mentions": [
        {
          "comment": 1, 
          "start": 99, 
          "end": 99
        }, 
        {
          "comment": 0, 
          "start": 98, 
          "end": 98
        }
      ]
    }
  ]
}