{
  "mentions": [
    {
      "volume": {
        "link": "http://tolstoy.ru/online/90/09/", 
        "number": 9, 
        "name": "Война и мир. Том первый"
      }, 
      "mentions": [
        {
          "comment": 0, 
          "start": 180, 
          "end": 180
        }
      ]
    }, 
    {
      "volume": {
        "link": "http://tolstoy.ru/online/90/13/", 
        "number": 13, 
        "name": "Война и мир: Черновые редакции и варианты (Часть 1)"
      }, 
      "mentions": [
        {
          "comment": 0, 
          "start": 468, 
          "end": 468
        }, 
        {
          "comment": 0, 
          "start": 439, 
          "end": 439
        }, 
        {
          "comment": 0, 
          "start": 373, 
          "end": 373
        }, 
        {
          "comment": 0, 
          "start": 371, 
          "end": 371
        }, 
        {
          "comment": 0, 
          "start": 355, 
          "end": 355
        }, 
        {
          "comment": 0, 
          "start": 342, 
          "end": 342
        }, 
        {
          "comment": 0, 
          "start": 333, 
          "end": 333
        }
      ]
    }
  ]
}