{
  "mentions": [
    {
      "volume": {
        "link": "http://tolstoy.ru/online/90/54/", 
        "number": 54, 
        "name": "Дневники, записные книжки и отдельные записки, 1900—1903"
      }, 
      "mentions": [
        {
          "comment": 1, 
          "start": 454, 
          "end": 454
        }, 
        {
          "comment": 0, 
          "start": 80, 
          "end": 80
        }
      ]
    }, 
    {
      "volume": {
        "link": "http://tolstoy.ru/online/90/71/", 
        "number": 71, 
        "name": "Письма, 1898"
      }, 
      "mentions": [
        {
          "comment": 0, 
          "start": 414, 
          "end": 414
        }, 
        {
          "comment": 1, 
          "start": 414, 
          "end": 414
        }
      ]
    }
  ]
}