{
  "mentions": [
    {
      "volume": {
        "link": "http://tolstoy.ru/online/90/58/", 
        "number": 58, 
        "name": "Дневники и записные книжки, 1910"
      }, 
      "mentions": [
        {
          "comment": 1, 
          "start": 330, 
          "end": 330
        }, 
        {
          "comment": 1, 
          "start": 242, 
          "end": 242
        }
      ]
    }, 
    {
      "volume": {
        "link": "http://tolstoy.ru/online/90/81/", 
        "number": 81, 
        "name": "Письма, 1910"
      }, 
      "mentions": [
        {
          "comment": 0, 
          "start": 150, 
          "end": 150
        }, 
        {
          "comment": 1, 
          "start": 121, 
          "end": 121
        }, 
        {
          "comment": 1, 
          "start": 120, 
          "end": 120
        }
      ]
    }
  ]
}