{
  "mentions": [
    {
      "volume": {
        "link": "http://tolstoy.ru/online/90/17/", 
        "number": 17, 
        "name": "Произведения, 1863, 1870, 1872—1879, 1884"
      }, 
      "mentions": [
        {
          "comment": 1, 
          "start": 610, 
          "end": 610
        }, 
        {
          "comment": 0, 
          "start": 122, 
          "end": 122
        }, 
        {
          "comment": 0, 
          "start": 101, 
          "end": 101
        }, 
        {
          "comment": 0, 
          "start": 97, 
          "end": 97
        }, 
        {
          "comment": 0, 
          "start": 93, 
          "end": 93
        }, 
        {
          "comment": 0, 
          "start": 89, 
          "end": 89
        }, 
        {
          "comment": 0, 
          "start": 88, 
          "end": 88
        }, 
        {
          "comment": 0, 
          "start": 87, 
          "end": 87
        }, 
        {
          "comment": 0, 
          "start": 83, 
          "end": 83
        }, 
        {
          "comment": 0, 
          "start": 80, 
          "end": 80
        }, 
        {
          "comment": 0, 
          "start": 76, 
          "end": 76
        }
      ]
    }
  ]
}