{
  "mentions": [
    {
      "volume": {
        "link": "http://tolstoy.ru/online/90/56/", 
        "number": 56, 
        "name": "Дневники, записные книжки и отдельные записки, 1907—1908"
      }, 
      "mentions": [
        {
          "comment": 1, 
          "start": 624, 
          "end": 624
        }, 
        {
          "comment": 1, 
          "start": 462, 
          "end": 462
        }, 
        {
          "comment": 1, 
          "start": 461, 
          "end": 461
        }, 
        {
          "comment": 0, 
          "start": 73, 
          "end": 73
        }
      ]
    }, 
    {
      "volume": {
        "link": "http://tolstoy.ru/online/90/77/", 
        "number": 77, 
        "name": "Письма, 1907—1908"
      }, 
      "mentions": [
        {
          "comment": 1, 
          "start": 260, 
          "end": 260
        }, 
        {
          "comment": 0, 
          "start": 227, 
          "end": 227
        }, 
        {
          "comment": 1, 
          "start": 227, 
          "end": 227
        }, 
        {
          "comment": 1, 
          "start": 202, 
          "end": 202
        }
      ]
    }, 
    {
      "volume": {
        "link": "http://tolstoy.ru/online/90/78/", 
        "number": 78, 
        "name": "Письма, 1908"
      }, 
      "mentions": [
        {
          "comment": 1, 
          "start": 365, 
          "end": 365
        }
      ]
    }, 
    {
      "volume": {
        "link": "http://tolstoy.ru/online/90/79/", 
        "number": 79, 
        "name": "Письма, 1909"
      }, 
      "mentions": [
        {
          "comment": 1, 
          "start": 280, 
          "end": 280
        }
      ]
    }
  ]
}