{
  "mentions": [
    {
      "volume": {
        "link": "http://tolstoy.ru/online/90/07/", 
        "number": 7, 
        "name": "Произведения, 1856—1869"
      }, 
      "mentions": [
        {
          "comment": 0, 
          "start": 220, 
          "end": 220
        }
      ]
    }, 
    {
      "volume": {
        "link": "http://tolstoy.ru/online/90/08/", 
        "number": 8, 
        "name": "Педагогические статьи, 1860—1863"
      }, 
      "mentions": [
        {
          "comment": 1, 
          "start": 569, 
          "end": 569
        }, 
        {
          "comment": 1, 
          "start": 537, 
          "end": 537
        }, 
        {
          "comment": 1, 
          "start": 465, 
          "end": 465
        }, 
        {
          "comment": 0, 
          "start": 292, 
          "end": 292
        }, 
        {
          "comment": 0, 
          "start": 265, 
          "end": 265
        }, 
        {
          "comment": 0, 
          "start": 264, 
          "end": 264
        }, 
        {
          "comment": 0, 
          "start": 257, 
          "end": 257
        }, 
        {
          "comment": 0, 
          "start": 144, 
          "end": 144
        }, 
        {
          "comment": 0, 
          "start": 136, 
          "end": 136
        }, 
        {
          "comment": 0, 
          "start": 133, 
          "end": 133
        }, 
        {
          "comment": 0, 
          "start": 126, 
          "end": 126
        }, 
        {
          "comment": 0, 
          "start": 60, 
          "end": 60
        }
      ]
    }, 
    {
      "volume": {
        "link": "http://tolstoy.ru/online/90/17/", 
        "number": 17, 
        "name": "Произведения, 1863, 1870, 1872—1879, 1884"
      }, 
      "mentions": [
        {
          "comment": 1, 
          "start": 610, 
          "end": 610
        }, 
        {
          "comment": 0, 
          "start": 103, 
          "end": 103
        }
      ]
    }
  ]
}