{
  "mentions": [
    {
      "volume": {
        "link": "http://tolstoy.ru/online/90/01/", 
        "number": 1, 
        "name": "Детство, юношеские опыты"
      }, 
      "mentions": [
        {
          "comment": 0, 
          "start": 278, 
          "end": 278
        }
      ]
    }, 
    {
      "volume": {
        "link": "http://tolstoy.ru/online/90/11/", 
        "number": 11, 
        "name": "Война и мир. Том третий"
      }, 
      "mentions": [
        {
          "comment": 0, 
          "start": 212, 
          "end": 212
        }, 
        {
          "comment": 0, 
          "start": 30, 
          "end": 30
        }
      ]
    }, 
    {
      "volume": {
        "link": "http://tolstoy.ru/online/90/12/", 
        "number": 12, 
        "name": "Война и мир. Том четвертый"
      }, 
      "mentions": [
        {
          "comment": 0, 
          "start": 297, 
          "end": 297
        }, 
        {
          "comment": 0, 
          "start": 239, 
          "end": 239
        }, 
        {
          "comment": 0, 
          "start": 121, 
          "end": 121
        }
      ]
    }, 
    {
      "volume": {
        "link": "http://tolstoy.ru/online/90/13/", 
        "number": 13, 
        "name": "Война и мир: Черновые редакции и варианты (Часть 1)"
      }, 
      "mentions": [
        {
          "comment": 0, 
          "start": 871, 
          "end": 871
        }, 
        {
          "comment": 0, 
          "start": 805, 
          "end": 805
        }
      ]
    }, 
    {
      "volume": {
        "link": "http://tolstoy.ru/online/90/14/", 
        "number": 14, 
        "name": "Война и мир: Черновые редакции и варианты (Часть 2)"
      }, 
      "mentions": [
        {
          "comment": 0, 
          "start": 344, 
          "end": 344
        }, 
        {
          "comment": 0, 
          "start": 266, 
          "end": 266
        }, 
        {
          "comment": 0, 
          "start": 32, 
          "end": 32
        }
      ]
    }, 
    {
      "volume": {
        "link": "http://tolstoy.ru/online/90/15/", 
        "number": 15, 
        "name": "Война и мир: Черновые редакции и варианты (Часть 3)"
      }, 
      "mentions": [
        {
          "comment": 0, 
          "start": 93, 
          "end": 93
        }
      ]
    }, 
    {
      "volume": {
        "link": "http://tolstoy.ru/online/90/17/", 
        "number": 17, 
        "name": "Произведения, 1863, 1870, 1872—1879, 1884"
      }, 
      "mentions": [
        {
          "comment": 0, 
          "start": 461, 
          "end": 461
        }, 
        {
          "comment": 0, 
          "start": 452, 
          "end": 452
        }, 
        {
          "comment": 0, 
          "start": 447, 
          "end": 447
        }
      ]
    }, 
    {
      "volume": {
        "link": "http://tolstoy.ru/online/90/18/", 
        "number": 18, 
        "name": "Анна Каренина. Части 1—4"
      }, 
      "mentions": [
        {
          "comment": 0, 
          "start": 373, 
          "end": 373
        }
      ]
    }, 
    {
      "volume": {
        "link": "http://tolstoy.ru/online/90/21/", 
        "number": 21, 
        "name": "Новая азбука и русские книги для чтения"
      }, 
      "mentions": [
        {
          "comment": 0, 
          "start": 364, 
          "end": 364
        }
      ]
    }, 
    {
      "volume": {
        "link": "http://tolstoy.ru/online/90/36/", 
        "number": 36, 
        "name": "Произведения, 1904—1906"
      }, 
      "mentions": [
        {
          "comment": 0, 
          "start": 197, 
          "end": 197
        }
      ]
    }, 
    {
      "volume": {
        "link": "http://tolstoy.ru/online/90/46/", 
        "number": 46, 
        "name": "Дневник, 1847—1854"
      }, 
      "mentions": [
        {
          "comment": 0, 
          "start": 271, 
          "end": 271
        }
      ]
    }, 
    {
      "volume": {
        "link": "http://tolstoy.ru/online/90/48/", 
        "number": 48, 
        "name": "Дневники и записные книжки, 1858—1880"
      }, 
      "mentions": [
        {
          "comment": 0, 
          "start": 194, 
          "end": 194
        }, 
        {
          "comment": 0, 
          "start": 109, 
          "end": 109
        }
      ]
    }, 
    {
      "volume": {
        "link": "http://tolstoy.ru/online/90/55/", 
        "number": 55, 
        "name": "Дневники и записные книжки, 1904—1906"
      }, 
      "mentions": [
        {
          "comment": 0, 
          "start": 214, 
          "end": 214
        }
      ]
    }
  ]
}