{
  "mentions": [
    {
      "volume": {
        "link": "http://tolstoy.ru/online/90/58/", 
        "number": 58, 
        "name": "Дневники и записные книжки, 1910"
      }, 
      "mentions": [
        {
          "comment": 1, 
          "start": 618, 
          "end": 618
        }, 
        {
          "comment": 1, 
          "start": 444, 
          "end": 444
        }, 
        {
          "comment": 0, 
          "start": 203, 
          "end": 203
        }, 
        {
          "comment": 0, 
          "start": 77, 
          "end": 77
        }
      ]
    }
  ]
}