{
  "mentions": [
    {
      "volume": {
        "link": "http://tolstoy.ru/online/90/17/", 
        "number": 17, 
        "name": "Произведения, 1863, 1870, 1872—1879, 1884"
      }, 
      "mentions": [
        {
          "comment": 1, 
          "start": 671, 
          "end": 671
        }, 
        {
          "comment": 1, 
          "start": 669, 
          "end": 669
        }, 
        {
          "comment": 1, 
          "start": 633, 
          "end": 633
        }, 
        {
          "comment": 0, 
          "start": 439, 
          "end": 439
        }, 
        {
          "comment": 0, 
          "start": 431, 
          "end": 431
        }, 
        {
          "comment": 0, 
          "start": 430, 
          "end": 430
        }, 
        {
          "comment": 0, 
          "start": 428, 
          "end": 428
        }, 
        {
          "comment": 0, 
          "start": 426, 
          "end": 426
        }
      ]
    }, 
    {
      "volume": {
        "link": "http://tolstoy.ru/online/90/48/", 
        "number": 48, 
        "name": "Дневники и записные книжки, 1858—1880"
      }, 
      "mentions": [
        {
          "comment": 1, 
          "start": 503, 
          "end": 503
        }, 
        {
          "comment": 1, 
          "start": 502, 
          "end": 502
        }, 
        {
          "comment": 1, 
          "start": 501, 
          "end": 501
        }, 
        {
          "comment": 0, 
          "start": 102, 
          "end": 102
        }, 
        {
          "comment": 0, 
          "start": 101, 
          "end": 101
        }, 
        {
          "comment": 0, 
          "start": 100, 
          "end": 100
        }
      ]
    }, 
    {
      "volume": {
        "link": "http://tolstoy.ru/online/90/62/", 
        "number": 62, 
        "name": "Письма, 1873—1879"
      }, 
      "mentions": [
        {
          "comment": 1, 
          "start": 6, 
          "end": 6
        }, 
        {
          "comment": 0, 
          "start": 5, 
          "end": 5
        }
      ]
    }
  ]
}