{
  "mentions": [
    {
      "volume": {
        "link": "http://tolstoy.ru/online/90/47/", 
        "number": 47, 
        "name": "Дневники и записные книжки, 1854—1857"
      }, 
      "mentions": [
        {
          "comment": 1, 
          "start": 340, 
          "end": 340
        }
      ]
    }, 
    {
      "volume": {
        "link": "http://tolstoy.ru/online/90/49/", 
        "number": 49, 
        "name": "Записки христианина, дневники и записные книжки, 1881—1887"
      }, 
      "mentions": [
        {
          "comment": 1, 
          "start": 219, 
          "end": 219
        }, 
        {
          "comment": 0, 
          "start": 74, 
          "end": 74
        }
      ]
    }
  ]
}