{
  "mentions": [
    {
      "volume": {
        "link": "http://tolstoy.ru/online/90/33/", 
        "number": 33, 
        "name": "Воскресение: Черновые редакции и варианты"
      }, 
      "mentions": [
        {
          "comment": 1, 
          "start": 428, 
          "end": 428
        }
      ]
    }, 
    {
      "volume": {
        "link": "http://tolstoy.ru/online/90/53/", 
        "number": 53, 
        "name": "Дневники и записные книжки, 1895—1899"
      }, 
      "mentions": [
        {
          "comment": 1, 
          "start": 432, 
          "end": 432
        }, 
        {
          "comment": 0, 
          "start": 39, 
          "end": 39
        }
      ]
    }, 
    {
      "volume": {
        "link": "http://tolstoy.ru/online/90/68/", 
        "number": 68, 
        "name": "Письма, 1895"
      }, 
      "mentions": [
        {
          "comment": 0, 
          "start": 160, 
          "end": 160
        }, 
        {
          "comment": 1, 
          "start": 160, 
          "end": 160
        }
      ]
    }
  ]
}