{
  "mentions": [
    {
      "volume": {
        "link": "http://tolstoy.ru/online/90/68/", 
        "number": 68, 
        "name": "Письма, 1895"
      }, 
      "mentions": [
        {
          "comment": 0, 
          "start": 218, 
          "end": 218
        }, 
        {
          "comment": 0, 
          "start": 215, 
          "end": 215
        }, 
        {
          "comment": 0, 
          "start": 158, 
          "end": 158
        }
      ]
    }, 
    {
      "volume": {
        "link": "http://tolstoy.ru/online/90/84/", 
        "number": 84, 
        "name": "Письма к С. А. Толстой, 1887—1910"
      }, 
      "mentions": [
        {
          "comment": 0, 
          "start": 270, 
          "end": 270
        }, 
        {
          "comment": 1, 
          "start": 270, 
          "end": 270
        }, 
        {
          "comment": 1, 
          "start": 241, 
          "end": 241
        }
      ]
    }
  ]
}