{
  "mentions": [
    {
      "volume": {
        "link": "http://tolstoy.ru/online/90/07/", 
        "number": 7, 
        "name": "Произведения, 1856—1869"
      }, 
      "mentions": [
        {
          "comment": 0, 
          "start": 308, 
          "end": 308
        }
      ]
    }, 
    {
      "volume": {
        "link": "http://tolstoy.ru/online/90/08/", 
        "number": 8, 
        "name": "Педагогические статьи, 1860—1863"
      }, 
      "mentions": [
        {
          "comment": 1, 
          "start": 584, 
          "end": 584
        }, 
        {
          "comment": 1, 
          "start": 543, 
          "end": 543
        }, 
        {
          "comment": 0, 
          "start": 444, 
          "end": 444
        }, 
        {
          "comment": 0, 
          "start": 442, 
          "end": 442
        }, 
        {
          "comment": 0, 
          "start": 343, 
          "end": 343
        }, 
        {
          "comment": 0, 
          "start": 335, 
          "end": 335
        }, 
        {
          "comment": 0, 
          "start": 225, 
          "end": 225
        }, 
        {
          "comment": 0, 
          "start": 106, 
          "end": 106
        }
      ]
    }, 
    {
      "volume": {
        "link": "http://tolstoy.ru/online/90/48/", 
        "number": 48, 
        "name": "Дневники и записные книжки, 1858—1880"
      }, 
      "mentions": [
        {
          "comment": 1, 
          "start": 433, 
          "end": 433
        }, 
        {
          "comment": 1, 
          "start": 374, 
          "end": 374
        }, 
        {
          "comment": 0, 
          "start": 15, 
          "end": 15
        }, 
        {
          "comment": 0, 
          "start": 14, 
          "end": 14
        }
      ]
    }, 
    {
      "volume": {
        "link": "http://tolstoy.ru/online/90/70/", 
        "number": 70, 
        "name": "Письма, 1897"
      }, 
      "mentions": [
        {
          "comment": 1, 
          "start": 203, 
          "end": 203
        }
      ]
    }
  ]
}